tracking_model/__init__.py
tracking_model/mixins.py
django_tracking_model-0.1.6.dist-info/LICENSE
django_tracking_model-0.1.6.dist-info/METADATA
django_tracking_model-0.1.6.dist-info/WHEEL
django_tracking_model-0.1.6.dist-info/top_level.txt
django_tracking_model-0.1.6.dist-info/RECORD
