Metadata-Version: 2.1
Name: django-tracking-model
Version: 0.1.6
Summary: Track changes made to django model instance fields.
Home-page: https://github.com/drozdowsky/django-tracking-model/
Author: drozdowsky
Author-email: hdrozdow+github@pm.me
License: MIT
License-File: LICENSE
Requires-Dist: Django >=1.11
